heaserver/activity/__init__.py
heaserver/activity/service.py
heaserver/activity/startup.py
heaserver/activity/wstl/all.json
heaserver_activity-1.7.0.dist-info/licenses/LICENSE
heaserver_activity-1.7.0.dist-info/METADATA
heaserver_activity-1.7.0.dist-info/WHEEL
heaserver_activity-1.7.0.dist-info/entry_points.txt
heaserver_activity-1.7.0.dist-info/top_level.txt
heaserver_activity-1.7.0.dist-info/RECORD
